setup.py
sunwatcher/__init__.py
sunwatcher.egg-info/PKG-INFO
sunwatcher.egg-info/SOURCES.txt
sunwatcher.egg-info/dependency_links.txt
sunwatcher.egg-info/requires.txt
sunwatcher.egg-info/top_level.txt
sunwatcher.egg-info/zip-safe
sunwatcher/ifttt/__init__.py
sunwatcher/ifttt/maker.py
sunwatcher/solarlog/__init__.py
sunwatcher/solarlog/client.py
sunwatcher/solarlog/solarlog.py